electrum_scripting/__init__.py
electrum_scripting/wallet.py
electrum_scripting-0.0.2.dist-info/LICENSE
electrum_scripting-0.0.2.dist-info/METADATA
electrum_scripting-0.0.2.dist-info/WHEEL
electrum_scripting-0.0.2.dist-info/top_level.txt
electrum_scripting-0.0.2.dist-info/zip-safe
electrum_scripting-0.0.2.dist-info/RECORD
