Metadata-Version: 2.1
Name: electrum-scripting
Version: 0.0.2
Summary: Electrum wallet scripting interface wrapper
Home-page: http://github.com/devfans/electrum-scripting
Author: Stefan Liu
Author-email: stefanliu@outlook.com
License: MIT
Keywords: Electrum Scripting Wallet Bitcoin Crypto
Platform: UNKNOWN
Classifier: License :: OSI Approved :: MIT License
Classifier: Topic :: Internet :: WWW/HTTP :: Dynamic Content
Classifier: Topic :: Software Development
Classifier: Programming Language :: Python :: 3
Classifier: Environment :: Web Environment
Classifier: Intended Audience :: Developers
Classifier: Operating System :: OS Independent
